iw4m/__init__.py
iw4m-0.4.9.dist-info/licenses/LICENSE
iw4m-0.4.9.dist-info/METADATA
iw4m-0.4.9.dist-info/WHEEL
iw4m-0.4.9.dist-info/top_level.txt
iw4m-0.4.9.dist-info/RECORD
