Metadata-Version: 2.4
Name: iw4m
Version: 0.4.9
Summary: A Python wrapper for the IW4M-Admin API
Home-page: https://github.com/Yallamaztar/iw4m
Author: budiworld
Author-email: budi.world@yahoo.com
Classifier: Programming Language :: Python :: 3
Classifier: License :: OSI Approved :: MIT License
Classifier: Operating System :: OS Independent
Requires-Python: >=3.6
License-File: LICENSE
Requires-Dist: requests
Requires-Dist: aiohttp
Requires-Dist: beautifulsoup4
Dynamic: author
Dynamic: author-email
Dynamic: classifier
Dynamic: description
Dynamic: description-content-type
Dynamic: home-page
Dynamic: license-file
Dynamic: requires-dist
Dynamic: requires-python
Dynamic: summary
